{
  "recentFiles": [
    {
      "basename": "Basics about ModelUpdating",
      "path": "ModelUpdating/Basics about ModelUpdating.md"
    },
    {
      "basename": "Math",
      "path": "Learn/Math/Math.md"
    },
    {
      "basename": "LearningRoute",
      "path": "Blog&Book&Paper/Write/LearningRoute.canvas"
    },
    {
      "basename": "Route.excalidraw",
      "path": "Blog&Book&Paper/Write/Route.excalidraw.md"
    },
    {
      "basename": "Interest.excalidraw",
      "path": "Blog&Book&Paper/Write/Interest.excalidraw.md"
    },
    {
      "basename": "NeuS-based 3D Reconstruction",
      "path": "3DReconstruction/NeuS-based 3D Reconstruction.md"
    },
    {
      "basename": "Paper about ModelUpdating",
      "path": "ModelUpdating/Paper about ModelUpdating.md"
    },
    {
      "basename": "Master Paper",
      "path": "Blog&Book&Paper/Write/Write Paper/3D Reconstruction/Master Paper.md"
    },
    {
      "basename": "Code of Multi-view 3D Reconstruction based on SDF and volume rendering",
      "path": "3DReconstruction/Code of Multi-view 3D Reconstruction based on SDF and volume rendering.md"
    },
    {
      "basename": "Finite Element Model 3D Reconstruction",
      "path": "3DReconstruction/Practical/Finite Element Model 3D Reconstruction.md"
    },
    {
      "basename": "NeRF-review",
      "path": "3DReconstruction/Multi-view/Implicit Function/NeRF-based/NeRF Other Research/NeRF-review.md"
    },
    {
      "basename": "Paper About 3D Reconstruction",
      "path": "3DReconstruction/Paper About 3D Reconstruction.md"
    },
    {
      "basename": "CAX",
      "path": "Other Interest/CAX.md"
    },
    {
      "basename": "3D Model",
      "path": "3DReconstruction/3D Model.md"
    },
    {
      "basename": "(WW) Isogeometric analysis",
      "path": "Blog&Book&Paper/Read/Papers/(WW) Isogeometric analysis.md"
    },
    {
      "basename": "MyGo",
      "path": "Blog&Book&Paper/Write/MyGo.md"
    },
    {
      "basename": "(BSF)Uncertainty",
      "path": "Blog&Book&Paper/Read/Papers/(BSF)Uncertainty.md"
    },
    {
      "basename": "Uncertainty",
      "path": "Other Interest/Uncertainty.md"
    },
    {
      "basename": "Book Lists",
      "path": "Blog&Book&Paper/Read/Book Lists.md"
    },
    {
      "basename": "Self-superviside Model Updating through inverse calibration model",
      "path": "Blog&Book&Paper/Write/Write Paper/Model Updating/Self-superviside Model Updating through inverse calibration model.md"
    },
    {
      "basename": "A fast interval model updating method based on MLP neural network",
      "path": "Blog&Book&Paper/Write/Write Paper/Model Updating/A fast interval model updating method based on MLP neural network.md"
    },
    {
      "basename": "A fast stochastic model updating technique based on an inverse FE surrogate model",
      "path": "Blog&Book&Paper/Write/Write Paper/Model Updating/A fast stochastic model updating technique based on an inverse FE surrogate model.md"
    },
    {
      "basename": "Dynamic Response Prediction (Deterministic)",
      "path": "Other Interest/Dynamic Response Prediction (Deterministic).md"
    },
    {
      "basename": "Case about ModelUpdating",
      "path": "ModelUpdating/Case about ModelUpdating.md"
    },
    {
      "basename": "Vibration Measurement",
      "path": "Other Interest/Vibration Measurement.md"
    },
    {
      "basename": "Dimensions  Measurement",
      "path": "3DReconstruction/Practical/Dimensions  Measurement.md"
    },
    {
      "basename": "(WX) Dynamics experiment",
      "path": "Blog&Book&Paper/Read/Papers/(WX) Dynamics experiment.md"
    },
    {
      "basename": "飞机算例数据集生成",
      "path": "Reports/PDF导出/飞机算例数据集生成.md"
    },
    {
      "basename": "Anime Image 3D Reconstruction",
      "path": "3DReconstruction/Practical/Anime Image 3D Reconstruction.md"
    },
    {
      "basename": "Multi-view Human Body Reconstruction",
      "path": "3DReconstruction/Practical/Multi-view Human Body Reconstruction.md"
    },
    {
      "basename": "Basics about 3D Reconstruction",
      "path": "3DReconstruction/Basics about 3D Reconstruction.md"
    },
    {
      "basename": "Automatic detection of pointer instrument",
      "path": "Project/Automatic detection of pointer instrument.md"
    },
    {
      "basename": "NeRF",
      "path": "Project/NeRF.md"
    },
    {
      "basename": "PyNastran",
      "path": "Project/PyNastran.md"
    },
    {
      "basename": "Python API",
      "path": "Project/Python API.md"
    },
    {
      "basename": "Python Scripts",
      "path": "Project/Python Scripts.md"
    },
    {
      "basename": "Python Spider",
      "path": "Project/Python Spider.md"
    },
    {
      "basename": "Six Legged Spider Robot",
      "path": "Project/Six Legged Spider Robot.md"
    },
    {
      "basename": "Unpack Snowbreak File",
      "path": "Project/Unpack Snowbreak File.md"
    },
    {
      "basename": "Visualize Interval uncertainty quantification metrics",
      "path": "Project/Visualize Interval uncertainty quantification metrics.md"
    },
    {
      "basename": "Other notes for obsidian",
      "path": "Reports/Other notes for obsidian.md"
    },
    {
      "basename": "人生七年",
      "path": "Blog&Book&Paper/Read/Book/人生七年.md"
    },
    {
      "basename": "A robust stochastic model updating method with resampling processing",
      "path": "ModelUpdating/Stochastic Model Updating/A robust stochastic model updating method with resampling processing.md"
    },
    {
      "basename": "参考文献",
      "path": "Reports/参考文献.md"
    },
    {
      "basename": "Data Analysis",
      "path": "Learn/Python/Data Analysis.md"
    },
    {
      "basename": "DeepLearning",
      "path": "Learn/Neural Network/DeepLearning.md"
    },
    {
      "basename": "Algorithm",
      "path": "Learn/Python/Algorithm.md"
    },
    {
      "basename": "Figure",
      "path": "Learn/Python/Figure.md"
    },
    {
      "basename": "Learn-Matlab",
      "path": "Learn/Finite Element/Learn-Matlab.md"
    },
    {
      "basename": "Tools",
      "path": "Blog&Book&Paper/Write/Source/Tools.md"
    }
  ],
  "omittedPaths": [],
  "omittedTags": [],
  "omitBookmarks": false,
  "maxLength": null,
  "openType": "tab"
}